teleos/__init__.py
teleos-0.0.2.dist-info/licenses/LICENSE
teleos-0.0.2.dist-info/METADATA
teleos-0.0.2.dist-info/WHEEL
teleos-0.0.2.dist-info/top_level.txt
teleos-0.0.2.dist-info/RECORD
