Metadata-Version: 2.4
Name: teleos
Version: 0.0.2
Summary: Package under development
Author: Your Name
Author-email: walletday@gmx.com
Classifier: Development Status :: 1 - Planning
Classifier: Programming Language :: Python :: 3
Requires-Python: >=3.6
License-File: LICENSE
Dynamic: author
Dynamic: author-email
Dynamic: classifier
Dynamic: description
Dynamic: description-content-type
Dynamic: license-file
Dynamic: requires-python
Dynamic: summary
